{
    "date": "",
    "macro": [
        {
            "id": "VIX",
            "name": "VIX Index",
            "value": 24.690000534057617,
            "status": "Amber",
            "note": "VIX at 24.69 (2025-11-18 4:00 PM EST). Elevated volatility. Monitor daily swings.",
            "action": "Monitor news flow; review volatility exposure.",
            "score_value": 1.0,
            "source_link": "https://www.cboe.com/vix/"
        },
        {
            "id": "GOLD_PRICE",
            "name": "Gold price (GLD proxy)",
            "value": 374.3500061035156,
            "status": "Red",
            "note": "Gold (GLD) at $374.35. Signals extreme flight to safety or high inflation expectations.",
            "action": "Maintain gold position as a core hedge; reduce risk assets.",
            "score_value": 1.0,
            "source_link": "https://finance.yahoo.com/quote/GLD"
        },
        {
            "id": "EURUSD",
            "name": "EUR/USD exchange rate",
            "value": 1.1587486267089844,
            "status": "Green",
            "note": "EUR/USD is at 1.1587. Normal range.",
            "action": "No change.",
            "score_value": 0.0,
            "source_link": "https://finance.yahoo.com/quote/EURUSD=X"
        },
        {
            "id": "WTI_CRUDE",
            "name": "WTI crude oil ($/bbl)",
            "value": 60.52000045776367,
            "status": "Green",
            "note": "WTI Crude at $60.52/bbl. Normal price range, favorable for growth.",
            "action": "No change.",
            "score_value": 0.0,
            "source_link": "https://finance.yahoo.com/quote/CL=F"
        },
        {
            "id": "AUDUSD",
            "name": "AUD/USD exchange rate",
            "value": 0.6485504508018494,
            "status": "Amber",
            "note": "AUDUSD at 0.6486. Weakness signals higher global risk aversion.",
            "action": "Monitor commodity markets and China growth data.",
            "score_value": 0.5,
            "source_link": "https://finance.yahoo.com/quote/AUDUSD=X"
        },
        {
            "id": "3Y_YIELD",
            "name": "US 3yr treasury yield",
            "value": 3.6,
            "status": "Green",
            "note": "Yield at 3.60%. Normal short-term rate environment.",
            "action": "No change.",
            "score_value": 0.0,
            "source_link": "https://www.treasury.gov/resource-center/data-chart-center/interest-rates/"
        },
        {
            "id": "30Y_YIELD",
            "name": "US 30yr treasury yield",
            "value": 4.73,
            "status": "Amber",
            "note": "Yield at 4.73%. Elevated long-term yields reflecting fiscal risk/inflation concerns.",
            "action": "Watch the 5.0% threshold. Limit long duration locks.",
            "score_value": 0.5,
            "source_link": "https://www.treasury.gov/resource-center/data-chart-center/interest-rates/"
        },
        {
            "id": "10Y_YIELD",
            "name": "US 10yr treasury yield",
            "value": 4.13,
            "status": "Green",
            "note": "Yield at 4.13%. Normal long-term rate environment.",
            "action": "No change.",
            "score_value": 0.0,
            "source_link": "https://www.treasury.gov/resource-center/data-chart-center/interest-rates/"
        },
        {
            "id": "HY_OAS",
            "name": "High yield OAS (bps)",
            "value": 313.0,
            "status": "Green",
            "note": "HY OAS at 313 bps. Spreads are tight. Indicates low corporate default risk.",
            "action": "No change.",
            "score_value": 0.0,
            "source_link": "https://fred.stlouisfed.org/series/BAMLH0A0HYM2"
        },
        {
            "id": "TREASURY_LIQUIDITY",
            "name": "Treasury net liquidity",
            "value": 5626645.095,
            "status": "Green",
            "note": "Net Liquidity at $5626645B. Liquidity is robust and supportive of risk assets.",
            "action": "No change.",
            "score_value": 0.0,
            "source_link": "https://fred.stlouisfed.org/series/WALCL"
        },
        {
            "id": "GEOPOLITICAL",
            "name": "Geopolitical risk",
            "value": "N/A",
            "status": "N/A",
            "note": "",
            "action": "No change.",
            "score_value": 0.0,
            "source_link": "Manual Input/Qualitative Assessment"
        },
        {
            "id": "FISCAL_RISK",
            "name": "Fiscal integrity/debt risk",
            "value": 25,
            "status": "Green",
            "note": "Fiscal Score is at 25. Risk is manageable based on current data.",
            "action": "Monitor VIX and SNAP data closely.",
            "score_value": 0.0,
            "source_link": "Composite/Internal Model (VIX, SNAP, CPI)"
        },
        {
            "id": "SNAP_BENEFITS",
            "name": "SNAP benefits (MoM % change)",
            "value": [
                111.15,
                97.391
            ],
            "status": "N/A",
            "note": "",
            "action": "No change.",
            "score_value": 0.0,
            "source_link": "https://fred.stlouisfed.org/series/SNPTA"
        },
        {
            "id": "BANK_CDS",
            "name": "Bank CDS (AAA Proxy, %)",
            "value": 5.13,
            "status": "Green",
            "note": "Bank CDS at 5 %. Low implied banking stress.",
            "action": "No change.",
            "score_value": 0.0,
            "source_link": "https://fred.stlouisfed.org/series/AAA"
        }
    ],
    "micro": [
        {
            "id": "SPX_INDEX",
            "name": "S&P 500 index",
            "value": 6617.31982421875,
            "status": "Green",
            "note": "S&P 500 Index at 6,617. Strong market momentum.",
            "action": "No change.",
            "score_value": 0.0,
            "source_link": "https://finance.yahoo.com/quote/%5EGSPC"
        },
        {
            "id": "ASX_200",
            "name": "ASX 200 index",
            "value": 8457.0,
            "status": "Green",
            "note": "ASX 200 Index at 8,457. Stable price action.",
            "action": "No change.",
            "score_value": 0.0,
            "source_link": "https://finance.yahoo.com/quote/%5EAXJO"
        },
        {
            "id": "MARGIN_DEBT_YOY",
            "name": "FINRA Margin Debt YOY %",
            "value": 38.52,
            "status": "Red",
            "note": "Margin Debt YOY at 38.5% (FINRA Data, Oct 2025, Not Seasonally Adjusted). Leverage is expanding aggressively. High risk of forced liquidation if markets fall.",
            "action": "Aggressively deleverage equity exposure; increase cash.",
            "score_value": 1.5,
            "source_link": "https://www.finra.org/investors/market-and-financial-data/margin-statistics"
        },
        {
            "id": "SMALL_LARGE_RATIO",
            "name": "Small/Large Cap Ratio (RUT/SPX)",
            "value": 0.35493826090106967,
            "status": "Red",
            "note": "Small/Large Cap ratio at 0.3549. Severe small-cap underperformance. Recessionary signal/high risk-off sentiment.",
            "action": "Avoid small-cap exposure entirely. Favour high-quality large-caps.",
            "score_value": 1.5,
            "source_link": "https://finance.yahoo.com/quote/%5ERUT"
        },
        {
            "id": "PUT_CALL_RATIO",
            "name": "Put/Call Ratio (PCCE)",
            "value": 1.3679165182361905,
            "status": "Red",
            "note": "SPY PCR at 1.3679. Extreme retail options hedging (put-buying). High market fear/bearish sentiment.",
            "action": "Consider contrarian bullish positioning; watch VIX for confirmation.",
            "score_value": 1.0,
            "source_link": "Data calculated from aggregated SPY options volume: [Yahoo Finance Link](https://finance.yahoo.com/quote/SPY)"
        },
        {
            "id": "SOFR_OIS",
            "name": "SOFR OIS Spread (%)",
            "value": 6.000000000000005,
            "status": "Green",
            "note": "SOFR/OIS spread is 6.00 %. Dollar funding market is stable.",
            "action": "No change.",
            "score_value": 0.0,
            "source_link": "https://fred.stlouisfed.org/series/TB3MS"
        },
        {
            "id": "CREDIT_CARD_DELINQUENCIES",
            "name": "Credit card delinquencies",
            "value": 305.0,
            "status": "Amber",
            "note": "Delinquency Rate at 305.0 bps. Rate is elevated. Caution on consumer lending quality.",
            "action": "Monitor consumer discretionary sector; review financial sector exposure.",
            "score_value": 0.75,
            "source_link": "https://fred.stlouisfed.org/series/DRCCLACBS"
        },
        {
            "id": "EARNINGS_REVISION",
            "name": "Earnings Revision Momentum",
            "value": "N/A",
            "status": "N/A",
            "note": "",
            "action": "No change.",
            "score_value": 0.0,
            "source_link": ""
        }
    ],
    "overall": {
        "date": "2025-11-19",
        "score": 7.75,
        "status": "ELEVATED RISK (MODERATE RISK)",
        "comment": "Caution warranted; mixed signals dominating market trends.",
        "raw_score_list": [
            1.0,
            1.0,
            0.0,
            0.0,
            0.5,
            0.0,
            0.5,
            0.0,
            0.0,
            0.0,
            0.0,
            0.0,
            0.0,
            0.0,
            0.0,
            0.0,
            1.5,
            1.5,
            1.0,
            0.0,
            0.75,
            0.0
        ],
        "escalation_watch": [
            {
                "name": "VIX Index",
                "value": "24.69",
                "threshold": "Above 18.0",
                "status": "Amber"
            },
            {
                "name": "10Y Yield",
                "value": "4.13",
                "threshold": "Above 4.0%",
                "status": "Green"
            }
        ],
        "daily_narrative": "The current overall risk posture is ELEVATED RISK (MODERATE RISK), with a Composite Score of 7.75, indicating a significant build-up of underlying vulnerabilities despite headline market resilience. Critical Red indicators driving this posture include the FINRA Margin Debt YOY % at 38.52, signaling excessive leverage within the system, and the Small/Large Cap Ratio (RUT/SPX) at 0.35, which highlights a concerning lack of market breadth and the underperformance of smaller, more rate-sensitive companies. This divergence suggests that market strength is concentrated in a few large-cap names, leaving the broader market susceptible to shifts in sentiment or liquidity. Furthermore, the Put/Call Ratio (PCCE) at 1.37 underscores elevated hedging activity or bearish sentiment, reflecting a cautious undercurrent among market participants who are actively seeking downside protection.\n\nThese leverage and market structure risks are compounded by an Amber VIX Index at 24.69 and a Red Gold price at 374.35, both indicative of rising volatility expectations and a flight to safety, respectively. The US 30yr treasury yield, at 4.73, is also Amber and nearing a critical threshold, signaling increasing duration risk across fixed income portfolios. A notable contradiction exists where the S&P 500 and ASX 200 remain in Green status, suggesting that broad equity indices have not yet fully priced in the underlying leverage and market structure fragilities. This disconnect implies that while speculative activity and market concentration are increasing, the immediate impact on headline equity performance is masked, potentially leading to a sharper correction when these internal stresses fully manifest. Investors should therefore be wary of concentrated market gains and assess portfolio resilience against a potential broadening of market weakness, particularly given the amber status of credit card delinquencies at 305.00, which points to nascent consumer leverage stress. This confluence of factors necessitates a vigilant approach to portfolio construction, emphasizing resilience against potential market dislocations before conditions deteriorate further.\n\nThe global macro and policy tone aligns with a cautious outlook, reinforcing the internal Atlas indicators of elevated risk. Global equity markets are exhibiting weakness, with Bloomberg and Morningstar reporting on continued losses for the FTSE 100 and broader European shares, partly attributed to ongoing concerns regarding AI valuations. This external market fragility resonates with our internal assessment of concentrated market strength and underlying structural vulnerabilities. Policy uncertainty persists, as Reuters highlights a deep policy divide within the Federal Reserve regarding future monetary actions, which contributes to market unease and duration risk. Concurrently, Reuters also points to a high-stakes budget in the UK, signaling potential fiscal challenges that could ripple through global markets. Inflationary pressures remain a concern, as evidenced by Bloomberg's reporting on the Reserve Bank of India's inflation miss, suggesting that central banks globally may face continued pressure to maintain restrictive policies. While some market commentary, as noted by Bloomberg, suggests that current pullbacks are merely healthy corrections rather than precursors to a bear market, the confluence of internal Atlas indicators and external macro headwinds warrants a defensive posture. Readers are directed to the News Feed below for the full list of articles reviewed. The posture would escalate to FULL-STORM if the US 10-Year Yield moves above 4.75% or HY OAS widens beyond 400 bps.",
        "composite_summary": "Atlas maintains an ELEVATED RISK (MODERATE RISK) posture, driven by rising leverage, market structure fragilities, and increasing duration risk, despite headline equity resilience.",
        "key_actions": [
            "Reduce exposure to highly leveraged positions and speculative assets.",
            "Overweight defensive sectors and high-quality, dividend-paying equities.",
            "Implement tactical hedges against potential equity market downside.",
            "Closely monitor high-yield credit spreads for any signs of significant widening.",
            "Reduce exposure to long-duration assets and highly rate-sensitive equities."
        ],
        "news": [
            {
                "title": "FTSE 100 Live: UK Stocks Set for Fourth Day of Losses in Global ...",
                "url": "https://www.bloomberg.com/news/live-blog/2025-11-18/ftse-100-bitcoin-price-stocks-selloff-reeves-uk-budget-what-s-moving-uk-markets-right-now-markets-today",
                "snippet": "Contextual article. Click title for details."
            },
            {
                "title": "BNY Mellon International Bond Fund Q3 2025 Commentary ...",
                "url": "https://seekingalpha.com/article/4845402-bny-mellon-international-bond-fund-q3-2025-commentary?source=feed_all_articles",
                "snippet": "Contextual article. Click title for details."
            },
            {
                "title": "Bob Diamond Sees Healthy Correction, Not Bear Market Precursor ...",
                "url": "https://www.bloomberg.com/news/articles/2025-11-19/bob-diamond-sees-healthy-correction-not-bear-market-precursor",
                "snippet": "Contextual article. Click title for details."
            },
            {
                "title": "High-stakes budget in store for edgy UK markets | Reuters",
                "url": "https://www.reuters.com/business/finance/high-stakes-budget-store-edgy-uk-markets-2025-11-19/",
                "snippet": "Contextual article. Click title for details."
            },
            {
                "title": "RBI's Big Inflation Miss Puts India Forecasts Under Scrutiny ...",
                "url": "https://www.bloomberg.com/news/articles/2025-11-19/rbi-s-big-inflation-misses-put-india-s-forecasts-under-scrutiny",
                "snippet": "Contextual article. Click title for details."
            },
            {
                "title": "Economics - Bloomberg",
                "url": "https://www.bloomberg.com/economics-v2",
                "snippet": "Contextual article. Click title for details."
            },
            {
                "title": "As data flow revives, Fed still faces a deep policy divide | Reuters",
                "url": "https://www.reuters.com/business/data-flow-revives-fed-still-faces-deep-policy-divide-2025-11-18/",
                "snippet": "Contextual article. Click title for details."
            },
            {
                "title": "Stock Market Today: Dow, S&P Live Updates for November 18 ...",
                "url": "https://www.bloomberg.com/news/articles/2025-11-17/asian-stocks-set-for-declines-as-selloff-deepens-markets-wrap",
                "snippet": "Contextual article. Click title for details."
            },
            {
                "title": "CEF Insights: Global High Income: Nuveen's Strategy And Outlook ...",
                "url": "https://seekingalpha.com/article/4844883-cef-insights-global-high-income-nuveen-strategy-outlook",
                "snippet": "Contextual article. Click title for details."
            },
            {
                "title": "European Midday Briefing: Shares Fall as AI Concerns Continue to ...",
                "url": "https://www.morningstar.com/news/dow-jones/202511182083/european-midday-briefing-shares-fall-as-ai-concerns-continue-to-weigh",
                "snippet": "Contextual article. Click title for details."
            }
        ],
        "news_context_raw": "1. [FTSE 100 Live: UK Stocks Set for Fourth Day of Losses in Global ...](https://www.bloomberg.com/news/live-blog/2025-11-18/ftse-100-bitcoin-price-stocks-selloff-reeves-uk-budget-what-s-moving-uk-markets-right-now-markets-today)\n2. [BNY Mellon International Bond Fund Q3 2025 Commentary ...](https://seekingalpha.com/article/4845402-bny-mellon-international-bond-fund-q3-2025-commentary?source=feed_all_articles)\n3. [Bob Diamond Sees Healthy Correction, Not Bear Market Precursor ...](https://www.bloomberg.com/news/articles/2025-11-19/bob-diamond-sees-healthy-correction-not-bear-market-precursor)\n4. [High-stakes budget in store for edgy UK markets | Reuters](https://www.reuters.com/business/finance/high-stakes-budget-store-edgy-uk-markets-2025-11-19/)\n5. [RBI's Big Inflation Miss Puts India Forecasts Under Scrutiny ...](https://www.bloomberg.com/news/articles/2025-11-19/rbi-s-big-inflation-misses-put-india-s-forecasts-under-scrutiny)\n6. [Economics - Bloomberg](https://www.bloomberg.com/economics-v2)\n7. [As data flow revives, Fed still faces a deep policy divide | Reuters](https://www.reuters.com/business/data-flow-revives-fed-still-faces-deep-policy-divide-2025-11-18/)\n8. [Stock Market Today: Dow, S&P Live Updates for November 18 ...](https://www.bloomberg.com/news/articles/2025-11-17/asian-stocks-set-for-declines-as-selloff-deepens-markets-wrap)\n9. [CEF Insights: Global High Income: Nuveen's Strategy And Outlook ...](https://seekingalpha.com/article/4844883-cef-insights-global-high-income-nuveen-strategy-outlook)\n10. [European Midday Briefing: Shares Fall as AI Concerns Continue to ...](https://www.morningstar.com/news/dow-jones/202511182083/european-midday-briefing-shares-fall-as-ai-concerns-continue-to-weigh)"
    }
}